xidi_ai/__init__.py
xidi_ai/_pytransform.dll
xidi_ai/license.lic
xidi_ai/pytransform.key
xidi_ai/pytransform.py
xidi_ai/care/__init__.py
xidi_ai/care/all_def.py
xidi_ai/care/classes/__init__.py
xidi_ai/care/classes/data_generator.py
xidi_ai/care/classes/losses.py
xidi_ai/care/classes/train.py
xidi_ai/care/classes/train_predict.py
xidi_ai/care/deg/__init__.py
xidi_ai/care/deg/train.py
xidi_ai/care/deg/train_predict.py
xidi_ai/care/deg/thirdParty/__init__.py
xidi_ai/care/deg/thirdParty/initializers.py
xidi_ai/care/deg/thirdParty/losses.py
xidi_ai/care/deg/thirdParty/backend/__init__.py
xidi_ai/care/deg/thirdParty/backend/common.py
xidi_ai/care/deg/thirdParty/backend/dynamic.py
xidi_ai/care/deg/thirdParty/backend/tensorflow_backend.py
xidi_ai/care/deg/thirdParty/bin/__init__.py
xidi_ai/care/deg/thirdParty/bin/base_model.py
xidi_ai/care/deg/thirdParty/callbacks/__init__.py
xidi_ai/care/deg/thirdParty/callbacks/coco.py
xidi_ai/care/deg/thirdParty/callbacks/common.py
xidi_ai/care/deg/thirdParty/callbacks/eval.py
xidi_ai/care/deg/thirdParty/layers/__init__.py
xidi_ai/care/deg/thirdParty/layers/_misc.py
xidi_ai/care/deg/thirdParty/layers/filter_detections.py
xidi_ai/care/deg/thirdParty/preprocessing/__init__.py
xidi_ai/care/deg/thirdParty/preprocessing/coco.py
xidi_ai/care/deg/thirdParty/preprocessing/csv_generator.py
xidi_ai/care/deg/thirdParty/preprocessing/generator.py
xidi_ai/care/deg/thirdParty/preprocessing/kitti.py
xidi_ai/care/deg/thirdParty/preprocessing/open_images.py
xidi_ai/care/deg/thirdParty/preprocessing/pascal_voc.py
xidi_ai/care/deg/thirdParty/utils/__init__.py
xidi_ai/care/deg/thirdParty/utils/anchors.py
xidi_ai/care/deg/thirdParty/utils/coco_eval.py
xidi_ai/care/deg/thirdParty/utils/colors.py
xidi_ai/care/deg/thirdParty/utils/config.py
xidi_ai/care/deg/thirdParty/utils/eval.py
xidi_ai/care/deg/thirdParty/utils/image.py
xidi_ai/care/deg/thirdParty/utils/keras_version.py
xidi_ai-0.0.2.dist-info/DESCRIPTION.rst
xidi_ai-0.0.2.dist-info/METADATA
xidi_ai-0.0.2.dist-info/RECORD
xidi_ai-0.0.2.dist-info/WHEEL
xidi_ai-0.0.2.dist-info/entry_points.txt
xidi_ai-0.0.2.dist-info/metadata.json
xidi_ai-0.0.2.dist-info/top_level.txt
