Metadata-Version: 2.0
Name: xidi-ai
Version: 0.0.2
Summary: ai tool
Home-page: UNKNOWN
Author: wangjinyi
Author-email: 1362681420@qq.com
License: MIT Licence
Keywords: xidi
Platform: UNKNOWN
Requires-Dist: opencv-python (==3.3.1.11)
Requires-Dist: tensorflow-gpu (==1.9.0)
Requires-Dist: pandas (==0.23.4)
Requires-Dist: numpy (==1.14.0)
Requires-Dist: imgaug (==0.2.6)
Requires-Dist: Keras (==2.2.4)
Requires-Dist: tqdm (==4.28.1)
Requires-Dist: h5py (>=2.8.0rc1)
Requires-Dist: six (==1.11.0)
